multidms/__init__.py
multidms/biophysical.py
multidms/data.py
multidms/jaxmodels.py
multidms/model.py
multidms/model_collection.py
multidms/plot.py
multidms/utils.py
multidms-1.2.0.dist-info/licenses/LICENSE
multidms-1.2.0.dist-info/METADATA
multidms-1.2.0.dist-info/WHEEL
multidms-1.2.0.dist-info/top_level.txt
multidms-1.2.0.dist-info/RECORD
