Metadata-Version: 2.4
Name: multidms
Version: 1.2.0
Summary: Joint modeling of multiple deep mutational scanning experiments.
Author-email: Jared Galloway <jgallowa@fredhutch.org>, Hugh Haddox <hkhaddox@gmail.com>
License: MIT License
Project-URL: repository, https://github.com/matsengrp/multidms
Keywords: multidms,generalized lasso,deep,mutational,scanning,dms,bloom,matsen
Classifier: License :: OSI Approved :: MIT License
Classifier: Programming Language :: Python
Classifier: Programming Language :: Python :: 3
Classifier: Programming Language :: Python :: 3.9
Requires-Python: >=3.9
License-File: LICENSE
Requires-Dist: polyclonal
Requires-Dist: jax>=0.4.29
Requires-Dist: jaxopt
Requires-Dist: typing_extensions
Requires-Dist: numpy
Requires-Dist: pandas>=2.2.0
Requires-Dist: binarymap>=0.7
Requires-Dist: altair==5.1.2
Requires-Dist: matplotlib
Requires-Dist: seaborn
Requires-Dist: scipy
Requires-Dist: scikit-learn
Requires-Dist: tqdm
Requires-Dist: equinox
Requires-Dist: pylops
Requires-Dist: pyproximal
Provides-Extra: dev
Requires-Dist: pytest; extra == "dev"
Requires-Dist: pytest-pep8; extra == "dev"
Requires-Dist: ruff; extra == "dev"
Requires-Dist: black~=23.3.0; extra == "dev"
Requires-Dist: notebook; extra == "dev"
Requires-Dist: sphinx==6.2.1; extra == "dev"
Requires-Dist: sphinx-autoapi==3.0.0; extra == "dev"
Requires-Dist: nbsphinx; extra == "dev"
Requires-Dist: nbsphinx_link; extra == "dev"
Requires-Dist: bumpver; extra == "dev"
Requires-Dist: sphinxcontrib-bibtex; extra == "dev"
Requires-Dist: dms_variants; extra == "dev"
Requires-Dist: ipywidgets; extra == "dev"
Dynamic: license-file
